l_converters/__init__.py
l_converters/converters.py
l_converters-1.0.3.dist-info/LICENSE
l_converters-1.0.3.dist-info/METADATA
l_converters-1.0.3.dist-info/WHEEL
l_converters-1.0.3.dist-info/top_level.txt
l_converters-1.0.3.dist-info/RECORD
