Metadata-Version: 2.1
Name: l-converters
Version: 1.0.3
Summary: Converters from smt to smt
Home-page: https://github.com/Sasha246sasha/l-converters
Author: Alexandr246
Author-email: alexandr246@vk.com
Keywords: converters python l md html
Classifier: Programming Language :: Python :: 3.9
Classifier: License :: OSI Approved :: MIT License
Classifier: Operating System :: OS Independent
Requires-Python: >=3.9
License-File: LICENSE
Requires-Dist: Markdown ==3.7
